<?xml version="1.0" encoding="UTF-8"?>
<!DOCTYPE mapper PUBLIC "-//mybatis.org//DTD Mapper 3.0//EN" "http://mybatis.org/dtd/mybatis-3-mapper.dtd">
<mapper namespace="com.easypay.cornucopiaallqrpay.dal.dao.TMchNotifyMapper">
  <resultMap id="BaseResultMap" type="com.easypay.cornucopiaallqrpay.dal.pojo.TMchNotify">
    <!--
      WARNING - @mbggenerated
      This element is automatically generated by MyBatis Generator, do not modify.
      This element was generated on Wed Apr 15 22:26:00 CST 2020.
    -->
    <id column="OrderId" jdbcType="VARCHAR" property="orderid" />
    <result column="MchId" jdbcType="VARCHAR" property="mchid" />
    <result column="MchOrderNo" jdbcType="VARCHAR" property="mchorderno" />
    <result column="OrderType" jdbcType="VARCHAR" property="ordertype" />
    <result column="NotifyUrl" jdbcType="VARCHAR" property="notifyurl" />
    <result column="NotifyCount" jdbcType="TINYINT" property="notifycount" />
    <result column="Result" jdbcType="VARCHAR" property="result" />
    <result column="Status" jdbcType="TINYINT" property="status" />
    <result column="LastNotifyTime" jdbcType="TIMESTAMP" property="lastnotifytime" />
    <result column="CreateTime" jdbcType="TIMESTAMP" property="createtime" />
    <result column="UpdateTime" jdbcType="TIMESTAMP" property="updatetime" />
  </resultMap>
  <sql id="Base_Column_List">
    <!--
      WARNING - @mbggenerated
      This element is automatically generated by MyBatis Generator, do not modify.
      This element was generated on Wed Apr 15 22:26:00 CST 2020.
    -->
    OrderId, MchId, MchOrderNo, OrderType, NotifyUrl, NotifyCount, Result, Status, LastNotifyTime, 
    CreateTime, UpdateTime
  </sql>
  <select id="selectByPrimaryKey" parameterType="java.lang.String" resultMap="BaseResultMap">
    <!--
      WARNING - @mbggenerated
      This element is automatically generated by MyBatis Generator, do not modify.
      This element was generated on Wed Apr 15 22:26:00 CST 2020.
    -->
    select 
    <include refid="Base_Column_List" />
    from t_mch_notify
    where OrderId = #{orderid,jdbcType=VARCHAR}
  </select>
  <delete id="deleteByPrimaryKey" parameterType="java.lang.String">
    <!--
      WARNING - @mbggenerated
      This element is automatically generated by MyBatis Generator, do not modify.
      This element was generated on Wed Apr 15 22:26:00 CST 2020.
    -->
    delete from t_mch_notify
    where OrderId = #{orderid,jdbcType=VARCHAR}
  </delete>
  <insert id="insert" parameterType="com.easypay.cornucopiaallqrpay.dal.pojo.TMchNotify">
    <!--
      WARNING - @mbggenerated
      This element is automatically generated by MyBatis Generator, do not modify.
      This element was generated on Wed Apr 15 22:26:00 CST 2020.
    -->
    insert into t_mch_notify (OrderId, MchId, MchOrderNo, 
      OrderType, NotifyUrl, NotifyCount, 
      Result, Status, LastNotifyTime, 
      CreateTime, UpdateTime)
    values (#{orderid,jdbcType=VARCHAR}, #{mchid,jdbcType=VARCHAR}, #{mchorderno,jdbcType=VARCHAR}, 
      #{ordertype,jdbcType=VARCHAR}, #{notifyurl,jdbcType=VARCHAR}, #{notifycount,jdbcType=TINYINT}, 
      #{result,jdbcType=VARCHAR}, #{status,jdbcType=TINYINT}, #{lastnotifytime,jdbcType=TIMESTAMP}, 
      #{createtime,jdbcType=TIMESTAMP}, #{updatetime,jdbcType=TIMESTAMP})
  </insert>
  <insert id="insertSelective" parameterType="com.easypay.cornucopiaallqrpay.dal.pojo.TMchNotify">
    <!--
      WARNING - @mbggenerated
      This element is automatically generated by MyBatis Generator, do not modify.
      This element was generated on Wed Apr 15 22:26:00 CST 2020.
    -->
    insert into t_mch_notify
    <trim prefix="(" suffix=")" suffixOverrides=",">
      <if test="orderid != null">
        OrderId,
      </if>
      <if test="mchid != null">
        MchId,
      </if>
      <if test="mchorderno != null">
        MchOrderNo,
      </if>
      <if test="ordertype != null">
        OrderType,
      </if>
      <if test="notifyurl != null">
        NotifyUrl,
      </if>
      <if test="notifycount != null">
        NotifyCount,
      </if>
      <if test="result != null">
        Result,
      </if>
      <if test="status != null">
        Status,
      </if>
      <if test="lastnotifytime != null">
        LastNotifyTime,
      </if>
      <if test="createtime != null">
        CreateTime,
      </if>
      <if test="updatetime != null">
        UpdateTime,
      </if>
    </trim>
    <trim prefix="values (" suffix=")" suffixOverrides=",">
      <if test="orderid != null">
        #{orderid,jdbcType=VARCHAR},
      </if>
      <if test="mchid != null">
        #{mchid,jdbcType=VARCHAR},
      </if>
      <if test="mchorderno != null">
        #{mchorderno,jdbcType=VARCHAR},
      </if>
      <if test="ordertype != null">
        #{ordertype,jdbcType=VARCHAR},
      </if>
      <if test="notifyurl != null">
        #{notifyurl,jdbcType=VARCHAR},
      </if>
      <if test="notifycount != null">
        #{notifycount,jdbcType=TINYINT},
      </if>
      <if test="result != null">
        #{result,jdbcType=VARCHAR},
      </if>
      <if test="status != null">
        #{status,jdbcType=TINYINT},
      </if>
      <if test="lastnotifytime != null">
        #{lastnotifytime,jdbcType=TIMESTAMP},
      </if>
      <if test="createtime != null">
        #{createtime,jdbcType=TIMESTAMP},
      </if>
      <if test="updatetime != null">
        #{updatetime,jdbcType=TIMESTAMP},
      </if>
    </trim>
  </insert>
  <update id="updateByPrimaryKeySelective" parameterType="com.easypay.cornucopiaallqrpay.dal.pojo.TMchNotify">
    <!--
      WARNING - @mbggenerated
      This element is automatically generated by MyBatis Generator, do not modify.
      This element was generated on Wed Apr 15 22:26:00 CST 2020.
    -->
    update t_mch_notify
    <set>
      <if test="mchid != null">
        MchId = #{mchid,jdbcType=VARCHAR},
      </if>
      <if test="mchorderno != null">
        MchOrderNo = #{mchorderno,jdbcType=VARCHAR},
      </if>
      <if test="ordertype != null">
        OrderType = #{ordertype,jdbcType=VARCHAR},
      </if>
      <if test="notifyurl != null">
        NotifyUrl = #{notifyurl,jdbcType=VARCHAR},
      </if>
      <if test="notifycount != null">
        NotifyCount = #{notifycount,jdbcType=TINYINT},
      </if>
      <if test="result != null">
        Result = #{result,jdbcType=VARCHAR},
      </if>
      <if test="status != null">
        Status = #{status,jdbcType=TINYINT},
      </if>
      <if test="lastnotifytime != null">
        LastNotifyTime = #{lastnotifytime,jdbcType=TIMESTAMP},
      </if>
      <if test="createtime != null">
        CreateTime = #{createtime,jdbcType=TIMESTAMP},
      </if>
      <if test="updatetime != null">
        UpdateTime = #{updatetime,jdbcType=TIMESTAMP},
      </if>
    </set>
    where OrderId = #{orderid,jdbcType=VARCHAR}
  </update>
  <update id="updateByPrimaryKey" parameterType="com.easypay.cornucopiaallqrpay.dal.pojo.TMchNotify">
    <!--
      WARNING - @mbggenerated
      This element is automatically generated by MyBatis Generator, do not modify.
      This element was generated on Wed Apr 15 22:26:00 CST 2020.
    -->
    update t_mch_notify
    set MchId = #{mchid,jdbcType=VARCHAR},
      MchOrderNo = #{mchorderno,jdbcType=VARCHAR},
      OrderType = #{ordertype,jdbcType=VARCHAR},
      NotifyUrl = #{notifyurl,jdbcType=VARCHAR},
      NotifyCount = #{notifycount,jdbcType=TINYINT},
      Result = #{result,jdbcType=VARCHAR},
      Status = #{status,jdbcType=TINYINT},
      LastNotifyTime = #{lastnotifytime,jdbcType=TIMESTAMP},
      CreateTime = #{createtime,jdbcType=TIMESTAMP},
      UpdateTime = #{updatetime,jdbcType=TIMESTAMP}
    where OrderId = #{orderid,jdbcType=VARCHAR}
  </update>
</mapper>